XuexiGoYuyanGolang/README.md
XuexiGoYuyanGolang/__init__.py
XuexiGoYuyanGolang/__main__.py
XuexiGoYuyanGolang/file.pdf
XuexiGoYuyanGolang/index.html
xuexi_go_yuyan_golang-2024.3.2.0.dist-info/METADATA
xuexi_go_yuyan_golang-2024.3.2.0.dist-info/WHEEL
xuexi_go_yuyan_golang-2024.3.2.0.dist-info/entry_points.txt
xuexi_go_yuyan_golang-2024.3.2.0.dist-info/top_level.txt
xuexi_go_yuyan_golang-2024.3.2.0.dist-info/RECORD
